setup.py
txrospy.py
txROSpy.egg-info/PKG-INFO
txROSpy.egg-info/SOURCES.txt
txROSpy.egg-info/dependency_links.txt
txROSpy.egg-info/requires.txt
txROSpy.egg-info/top_level.txt