Metadata-Version: 1.0
Name: txROSpy
Version: 0.1
Summary: Twisted port of the ROS protocols
Home-page: http://github.com/esteve/txrospy
Author: Esteve Fernandez
Author-email: esteve@apache.org
License: UNKNOWN
Platform: UNKNOWN
